<?xml version="1.0" encoding="UTF-8"?>
<ruleset name="BidMart PMD Rules (Main)"
         xmlns="http://pmd.sourceforge.net/ruleset/2.0.0"
         xmlns:xsi="http://www.w3.org/2001/XMLSchema-instance"
         xsi:schemaLocation="http://pmd.sourceforge.net/ruleset/2.0.0 https://pmd.sourceforge.net/ruleset_2_0_0.xsd">

  <description>PMD rules for production/main source set.</description>

  <rule ref="category/java/bestpractices.xml"/>

  <rule ref="category/java/design.xml">
    <exclude name="LoosePackageCoupling"/>
    <exclude name="UseUtilityClass"/>
    <exclude name="SignatureDeclareThrowsException"/>
  </rule>

  <rule ref="category/java/errorprone.xml"/>
</ruleset>